collective.voltoeditortemplates-1.0a3-py3.11-nspkg.pth
collective/voltoeditortemplates/__init__.py
collective/voltoeditortemplates/configure.zcml
collective/voltoeditortemplates/dependencies.zcml
collective/voltoeditortemplates/interfaces.py
collective/voltoeditortemplates/permissions.zcml
collective/voltoeditortemplates/profiles.zcml
collective/voltoeditortemplates/testing.py
collective/voltoeditortemplates/content/__init__.py
collective/voltoeditortemplates/controlpanel/__init__.py
collective/voltoeditortemplates/controlpanel/configure.zcml
collective/voltoeditortemplates/controlpanel/settings.py
collective/voltoeditortemplates/indexers/__init__.py
collective/voltoeditortemplates/indexers/configure.zcml
collective/voltoeditortemplates/locales/__init__.py
collective/voltoeditortemplates/locales/collective.voltoeditortemplates.pot
collective/voltoeditortemplates/locales/update.py
collective/voltoeditortemplates/locales/en/LC_MESSAGES/collective.voltoeditortemplates.po
collective/voltoeditortemplates/profiles/default/actions.xml
collective/voltoeditortemplates/profiles/default/browserlayer.xml
collective/voltoeditortemplates/profiles/default/catalog.xml
collective/voltoeditortemplates/profiles/default/controlpanel.xml
collective/voltoeditortemplates/profiles/default/diff_tool.xml
collective/voltoeditortemplates/profiles/default/metadata.xml
collective/voltoeditortemplates/profiles/default/repositorytool.xml
collective/voltoeditortemplates/profiles/default/rolemap.xml
collective/voltoeditortemplates/profiles/default/theme.xml
collective/voltoeditortemplates/profiles/default/types.xml
collective/voltoeditortemplates/profiles/default/registry/main.xml
collective/voltoeditortemplates/profiles/default/types/.gitkeep
collective/voltoeditortemplates/profiles/uninstall/browserlayer.xml
collective/voltoeditortemplates/restapi/__init__.py
collective/voltoeditortemplates/restapi/configure.zcml
collective/voltoeditortemplates/restapi/controlpanels.py
collective.voltoeditortemplates-1.0a3.dist-info/LICENSE
collective.voltoeditortemplates-1.0a3.dist-info/LICENSE.GPL
collective.voltoeditortemplates-1.0a3.dist-info/LICENSE.md
collective.voltoeditortemplates-1.0a3.dist-info/METADATA
collective.voltoeditortemplates-1.0a3.dist-info/WHEEL
collective.voltoeditortemplates-1.0a3.dist-info/entry_points.txt
collective.voltoeditortemplates-1.0a3.dist-info/namespace_packages.txt
collective.voltoeditortemplates-1.0a3.dist-info/top_level.txt
collective.voltoeditortemplates-1.0a3.dist-info/RECORD
